beir/__init__.py
beir/logging.py
beir/util.py
beir/datasets/__init__.py
beir/datasets/data_loader.py
beir/datasets/data_loader_hf.py
beir/generation/__init__.py
beir/generation/generate.py
beir/generation/models/__init__.py
beir/generation/models/auto_model.py
beir/generation/models/tilde.py
beir/losses/__init__.py
beir/losses/bpr_loss.py
beir/losses/margin_mse_loss.py
beir/reranking/__init__.py
beir/reranking/rerank.py
beir/reranking/models/__init__.py
beir/reranking/models/cross_encoder.py
beir/reranking/models/mono_t5.py
beir/retrieval/__init__.py
beir/retrieval/custom_metrics.py
beir/retrieval/evaluation.py
beir/retrieval/train.py
beir/retrieval/apis/__init__.py
beir/retrieval/apis/cohere.py
beir/retrieval/apis/voyage.py
beir/retrieval/models/__init__.py
beir/retrieval/models/bpr.py
beir/retrieval/models/huggingface.py
beir/retrieval/models/llm2vec.py
beir/retrieval/models/nvembed.py
beir/retrieval/models/pooling.py
beir/retrieval/models/sentence_bert.py
beir/retrieval/models/sparta.py
beir/retrieval/models/splade.py
beir/retrieval/models/tldr.py
beir/retrieval/models/unicoil.py
beir/retrieval/models/util.py
beir/retrieval/models/vllm.py
beir/retrieval/search/__init__.py
beir/retrieval/search/base.py
beir/retrieval/search/dense/__init__.py
beir/retrieval/search/dense/exact_search.py
beir/retrieval/search/dense/exact_search_multi_gpu.py
beir/retrieval/search/dense/faiss_index.py
beir/retrieval/search/dense/faiss_search.py
beir/retrieval/search/dense/util.py
beir/retrieval/search/lexical/__init__.py
beir/retrieval/search/lexical/bm25_search.py
beir/retrieval/search/lexical/elastic_search.py
beir/retrieval/search/sparse/__init__.py
beir/retrieval/search/sparse/sparse_search.py
beir-2.2.0.dist-info/licenses/LICENSE
beir-2.2.0.dist-info/licenses/NOTICE.txt
beir-2.2.0.dist-info/METADATA
beir-2.2.0.dist-info/WHEEL
beir-2.2.0.dist-info/top_level.txt
beir-2.2.0.dist-info/RECORD
