Metadata-Version: 2.4
Name: beir
Version: 2.2.0
Summary: A Heterogeneous Benchmark for Information Retrieval
Author-email: Nandan Thakur <nandant@gmail.com>
Maintainer-email: Nandan Thakur <nandant@gmail.com>
License: Apache License 2.0
Project-URL: Homepage, https://github.com/beir-cellar/beir
Project-URL: Repository, https://github.com/beir-cellar/beir
Project-URL: Download, https://github.com/beir-cellar/beir/archive/v2.2.0.zip
Keywords: Benchmarking,BEIR,Evaluation Framework,Information Retrieval,Transformer Networks,Large Language Models,PyTorch,RAG,IR,NLP,Deep Learning
Classifier: Development Status :: 4 - Beta
Classifier: Intended Audience :: Science/Research
Classifier: License :: OSI Approved :: Apache Software License
Classifier: Programming Language :: Python :: 3.9
Classifier: Programming Language :: Python :: 3.10
Classifier: Programming Language :: Python :: 3.11
Classifier: Programming Language :: Python :: 3.12
Classifier: Topic :: Scientific/Engineering :: Artificial Intelligence
Requires-Python: >=3.9
License-File: LICENSE
License-File: NOTICE.txt
Requires-Dist: sentence-transformers
Requires-Dist: pytrec-eval-terrier
Requires-Dist: datasets
Provides-Extra: tf
Requires-Dist: tensorflow>=2.2.0; extra == "tf"
Requires-Dist: tensorflow-text; extra == "tf"
Requires-Dist: tensorflow-hub; extra == "tf"
Provides-Extra: elasticsearch
Requires-Dist: elasticsearch==7.9.1; extra == "elasticsearch"
Provides-Extra: peft
Requires-Dist: peft; extra == "peft"
Provides-Extra: llm2vec
Requires-Dist: llm2vec; extra == "llm2vec"
Provides-Extra: dev
Requires-Dist: pytest; extra == "dev"
Requires-Dist: pytest-cov; extra == "dev"
Requires-Dist: pre-commit; extra == "dev"
Provides-Extra: faiss
Requires-Dist: faiss-cpu; extra == "faiss"
Dynamic: license-file
